openctp_client/__init__.py
openctp_client/clients/__init__.py
openctp_client/clients/simple_ctp_client.py
openctp_client/objects/__init__.py
openctp_client/objects/config.py
openctp_client/objects/enums.py
openctp_client/objects/fields.py
openctp_client/objects/requests.py
openctp_client/objects/responses.py
openctp_client-6.6.7.1.dist-info/METADATA
openctp_client-6.6.7.1.dist-info/WHEEL
openctp_client-6.6.7.1.dist-info/licenses/LICENSE
openctp_client-6.6.7.1.dist-info/RECORD
